iansface.py
setup.py
iansface.egg-info/PKG-INFO
iansface.egg-info/SOURCES.txt
iansface.egg-info/dependency_links.txt
iansface.egg-info/entry_points.txt
iansface.egg-info/top_level.txt