Metadata-Version: 1.1
Name: iansface
Version: 1.1
Summary: A module for printing Ian's face.
Home-page: http://github.com/gigawhitlocks/myface
Author: gigawhitlocks
Author-email: giggles@alum.hackerschool.com
License: UNKNOWN
Download-URL: https://github.com/gigawhitlocks/myface/archive/master.zip
Platform: UNKNOWN
